profanity-check/__init__.py
profanity_check/__init__.py
profanity_check/profanity_check.py
profanity_check/data/model.joblib
profanity_check/data/vectorizer.joblib
tests/__init__.py
tests/test_profanity_check.py
profanity_check-1.0.2.dist-info/LICENSE
profanity_check-1.0.2.dist-info/METADATA
profanity_check-1.0.2.dist-info/WHEEL
profanity_check-1.0.2.dist-info/top_level.txt
profanity_check-1.0.2.dist-info/RECORD
