Metadata-Version: 2.1
Name: profanity-check
Version: 1.0.2
Summary: A fast, robust library to check for offensive language in strings.
Home-page: https://github.com/vzhou842/profanity-check
Author: Victor Zhou
Author-email: vzhou842@gmail.com
License: UNKNOWN
Platform: UNKNOWN
Classifier: Development Status :: 5 - Production/Stable
Classifier: Natural Language :: English
Classifier: Programming Language :: Python :: 3
Classifier: License :: OSI Approved :: MIT License
Classifier: Operating System :: OS Independent
Requires-Dist: scikit-learn (==0.20.2)
